{
  "crawledAt": "2026-05-06T03:28:13.547Z",
  "count": 65,
  "items": [
    {
      "seq": "4688",
      "title": "강릉 도시관리계획(공간시설: 소공원) 결정(안) 열람·공고",
      "noticeNumber": "강원특별자치도 강릉시 공고 제2026-823호",
      "agency": "강원특별자치도 강릉시 도시교통국 도시과",
      "publishedAt": "2026-05-06",
      "hearingStartDate": "2026-05-06",
      "hearingEndDate": "2026-05-20",
      "detailUrl": "https://www.eum.go.kr/web/cp/hr/hrPeopleHearDet.jsp?seq=4688&pageNo=1&zonenm=&startdt=&enddt=&chrgorg=&selSggCd=&select2=&select_3=&gosino=&mobile_yn=",
      "listPage": 1
    },
    {
      "seq": "4686",
      "title": "철원 군관리계획(시설:어린이공원, 공원조성계획) 결정(안) 공람ㆍ공고",
      "noticeNumber": "강원특별자치도 철원군 공고 제2026-740호",
      "agency": "강원특별자치도 철원군 건설도시과",
      "publishedAt": "2026-05-06",
      "hearingStartDate": "2026-05-06",
      "hearingEndDate": "2026-05-21",
      "detailUrl": "https://www.eum.go.kr/web/cp/hr/hrPeopleHearDet.jsp?seq=4686&pageNo=1&zonenm=&startdt=&enddt=&chrgorg=&selSggCd=&select2=&select_3=&gosino=&mobile_yn=",
      "listPage": 1
    },
    {
      "seq": "4682",
      "title": "구미 도시관리계획(연구시설) 결정(변경)(안) 공람공고",
      "noticeNumber": "경상북도 구미시 공고 제2026-1454호",
      "agency": "경상북도 구미시 도시건설국 도시계획과",
      "publishedAt": "2026-05-04",
      "hearingStartDate": "2026-05-04",
      "hearingEndDate": "2026-05-27",
      "detailUrl": "https://www.eum.go.kr/web/cp/hr/hrPeopleHearDet.jsp?seq=4682&pageNo=1&zonenm=&startdt=&enddt=&chrgorg=&selSggCd=&select2=&select_3=&gosino=&mobile_yn=",
      "listPage": 1
    },
    {
      "seq": "4680",
      "title": "군포도시관리계획[환경기초시설:하수도(공공하수처리시설)] 결정(변경)(안) 열람·공고",
      "noticeNumber": "경기도 군포시 공고 제2026-646호",
      "agency": "경기도 군포시 도시주택국 도시계획과",
      "publishedAt": "2026-05-04",
      "hearingStartDate": "2026-05-04",
      "hearingEndDate": "2026-05-26",
      "detailUrl": "https://www.eum.go.kr/web/cp/hr/hrPeopleHearDet.jsp?seq=4680&pageNo=1&zonenm=&startdt=&enddt=&chrgorg=&selSggCd=&select2=&select_3=&gosino=&mobile_yn=",
      "listPage": 1
    },
    {
      "seq": "4664",
      "title": "고창 군관리계획(군계획시설:공원) 결정(변경) 및 공원 조성계획 결정(안)에 대한 재열람·공고",
      "noticeNumber": "전북특별자치도 고창군 공고 제2026-919호",
      "agency": "전북특별자치도 고창군 안전건설국 도시디자인과",
      "publishedAt": "2026-05-04",
      "hearingStartDate": "2026-05-04",
      "hearingEndDate": "2026-05-18",
      "detailUrl": "https://www.eum.go.kr/web/cp/hr/hrPeopleHearDet.jsp?seq=4664&pageNo=1&zonenm=&startdt=&enddt=&chrgorg=&selSggCd=&select2=&select_3=&gosino=&mobile_yn=",
      "listPage": 1
    },
    {
      "seq": "4649",
      "title": "의정부 도시관리계획(개발제한구역해제 취락지구 지구단위계획) 결정(변경)(안) 공람(4차) 공고",
      "noticeNumber": "경기도 의정부시 공고 제2026-965호",
      "agency": "경기도 의정부시 도시주택국 도시정책과",
      "publishedAt": "2026-05-04",
      "hearingStartDate": "2026-05-04",
      "hearingEndDate": "2026-05-18",
      "detailUrl": "https://www.eum.go.kr/web/cp/hr/hrPeopleHearDet.jsp?seq=4649&pageNo=1&zonenm=&startdt=&enddt=&chrgorg=&selSggCd=&select2=&select_3=&gosino=&mobile_yn=",
      "listPage": 1
    },
    {
      "seq": "4646",
      "title": "영양 군관리계획(학교) 결정(폐지)(안) 공람공고",
      "noticeNumber": "경상북도 영양군 공고 제2026-447호",
      "agency": "경상북도 영양군 지역개발과",
      "publishedAt": "2026-05-04",
      "hearingStartDate": "2026-05-04",
      "hearingEndDate": "2026-05-18",
      "detailUrl": "https://www.eum.go.kr/web/cp/hr/hrPeopleHearDet.jsp?seq=4646&pageNo=1&zonenm=&startdt=&enddt=&chrgorg=&selSggCd=&select2=&select_3=&gosino=&mobile_yn=",
      "listPage": 1
    },
    {
      "seq": "4687",
      "title": "예천 군관리계획(공원, 공원조성계획) 결정(변경)(안) 공람공고",
      "noticeNumber": "경상북도 예천군 공고 제2026-738호",
      "agency": "경상북도 예천군 도시과",
      "publishedAt": "2026-04-30",
      "hearingStartDate": "2026-04-30",
      "hearingEndDate": "2026-05-14",
      "detailUrl": "https://www.eum.go.kr/web/cp/hr/hrPeopleHearDet.jsp?seq=4687&pageNo=1&zonenm=&startdt=&enddt=&chrgorg=&selSggCd=&select2=&select_3=&gosino=&mobile_yn=",
      "listPage": 1
    },
    {
      "seq": "4681",
      "title": "금호동1가 129번지 일대 모아타운 지정을 위한 소규모주택정비 관리계획 수립(안) 주민공람 공고",
      "noticeNumber": "서울특별시 성동구 공고 제2026-661호",
      "agency": "서울특별시 성동구 도시관리국 주거정비과",
      "publishedAt": "2026-04-30",
      "hearingStartDate": "2026-04-30",
      "hearingEndDate": "2026-05-14",
      "detailUrl": "https://www.eum.go.kr/web/cp/hr/hrPeopleHearDet.jsp?seq=4681&pageNo=1&zonenm=&startdt=&enddt=&chrgorg=&selSggCd=&select2=&select_3=&gosino=&mobile_yn=",
      "listPage": 1
    },
    {
      "seq": "4676",
      "title": "의령군관리계획[교통시설:도로(소로2-53호선, 소로3-36호선)] 결정(변경)을 위한 공람 공고",
      "noticeNumber": "경상남도 의령군 공고 제2026-545호",
      "agency": "경상남도 의령군 산업건설국 도시재생과",
      "publishedAt": "2026-04-30",
      "hearingStartDate": "2026-04-30",
      "hearingEndDate": "2026-05-14",
      "detailUrl": "https://www.eum.go.kr/web/cp/hr/hrPeopleHearDet.jsp?seq=4676&pageNo=1&zonenm=&startdt=&enddt=&chrgorg=&selSggCd=&select2=&select_3=&gosino=&mobile_yn=",
      "listPage": 1
    },
    {
      "seq": "4675",
      "title": "의령군관리계획[교통시설:도로(소로2-117호선)] 결정(변경)을 위한 공람 공고",
      "noticeNumber": "경상남도 의령군 공고 제2026-544호",
      "agency": "경상남도 의령군 산업건설국 도시재생과",
      "publishedAt": "2026-04-30",
      "hearingStartDate": "2026-04-30",
      "hearingEndDate": "2026-05-14",
      "detailUrl": "https://www.eum.go.kr/web/cp/hr/hrPeopleHearDet.jsp?seq=4675&pageNo=2&zonenm=&startdt=&enddt=&chrgorg=&selSggCd=&select2=&select_3=&gosino=&mobile_yn=",
      "listPage": 2
    },
    {
      "seq": "4674",
      "title": "도시계획시설(도로)사업 실시계획인가를 위한  주민 등의 의견청취 공고",
      "noticeNumber": "충청남도 보령시 공고 제2026-868호",
      "agency": "충청남도 보령시 경제도시국 도시과",
      "publishedAt": "2026-04-30",
      "hearingStartDate": "2026-04-30",
      "hearingEndDate": "2026-05-14",
      "detailUrl": "https://www.eum.go.kr/web/cp/hr/hrPeopleHearDet.jsp?seq=4674&pageNo=2&zonenm=&startdt=&enddt=&chrgorg=&selSggCd=&select2=&select_3=&gosino=&mobile_yn=",
      "listPage": 2
    },
    {
      "seq": "4672",
      "title": "DDP 1·2·3 구역 도시정비형 재개발사업 정비구역 지정 및 정비계획 결정(안) 공람？공고",
      "noticeNumber": "서울특별시 중구 공고 제2026-501호",
      "agency": "서울특별시 중구 도시관리국 도심정비과",
      "publishedAt": "2026-04-30",
      "hearingStartDate": "2026-04-30",
      "hearingEndDate": "2026-05-14",
      "detailUrl": "https://www.eum.go.kr/web/cp/hr/hrPeopleHearDet.jsp?seq=4672&pageNo=2&zonenm=&startdt=&enddt=&chrgorg=&selSggCd=&select2=&select_3=&gosino=&mobile_yn=",
      "listPage": 2
    },
    {
      "seq": "4671",
      "title": "삼척 도시관리계획(시설：도로) 결정(변경)(안) 주민 열람 공고",
      "noticeNumber": "강원특별자치도 삼척시 공고 제2026-748호",
      "agency": "강원특별자치도 삼척시 안전건설국 도시과",
      "publishedAt": "2026-04-30",
      "hearingStartDate": "2026-04-30",
      "hearingEndDate": "2026-05-16",
      "detailUrl": "https://www.eum.go.kr/web/cp/hr/hrPeopleHearDet.jsp?seq=4671&pageNo=2&zonenm=&startdt=&enddt=&chrgorg=&selSggCd=&select2=&select_3=&gosino=&mobile_yn=",
      "listPage": 2
    },
    {
      "seq": "4670",
      "title": "추자B지구 도시관리계획(용도지역, 지구단위계획구역, 지구단위계획) 결정(변경)(안) 및 전략환경영향평가 초안 주민열람 공고",
      "noticeNumber": "경기도 광주시 공고 제2026-1285호",
      "agency": "경기도 광주시 도시주택국 도시계획과",
      "publishedAt": "2026-04-30",
      "hearingStartDate": "2026-04-30",
      "hearingEndDate": "2026-05-14",
      "detailUrl": "https://www.eum.go.kr/web/cp/hr/hrPeopleHearDet.jsp?seq=4670&pageNo=2&zonenm=&startdt=&enddt=&chrgorg=&selSggCd=&select2=&select_3=&gosino=&mobile_yn=",
      "listPage": 2
    },
    {
      "seq": "4668",
      "title": "양양 군관리계획(지구단위계획구역 등) 결정(변경)(안) (재)열람 공고",
      "noticeNumber": "강원특별자치도 양양군 공고 제2026-487호",
      "agency": "강원특별자치도 양양군 도시계획과",
      "publishedAt": "2026-04-30",
      "hearingStartDate": "2026-04-30",
      "hearingEndDate": "2026-05-15",
      "detailUrl": "https://www.eum.go.kr/web/cp/hr/hrPeopleHearDet.jsp?seq=4668&pageNo=2&zonenm=&startdt=&enddt=&chrgorg=&selSggCd=&select2=&select_3=&gosino=&mobile_yn=",
      "listPage": 2
    },
    {
      "seq": "4666",
      "title": "구미 도시관리계획(구평2지구 지구단위계획) 결정(변경)(안) 공람·공고",
      "noticeNumber": "경상북도 구미시 공고 제2026-1435호",
      "agency": "경상북도 구미시 도시건설국 공공시설과",
      "publishedAt": "2026-04-30",
      "hearingStartDate": "2026-04-30",
      "hearingEndDate": "2026-05-22",
      "detailUrl": "https://www.eum.go.kr/web/cp/hr/hrPeopleHearDet.jsp?seq=4666&pageNo=2&zonenm=&startdt=&enddt=&chrgorg=&selSggCd=&select2=&select_3=&gosino=&mobile_yn=",
      "listPage": 2
    },
    {
      "seq": "4662",
      "title": "도시관리계획[동작구 신대방지구 지구단위계획구역 및 계획(재정비)] 결정(변경)(안) 재열람공고",
      "noticeNumber": "서울특별시 동작구 공고 제2026-868호",
      "agency": "서울특별시 동작구 도시교통국 도시계획과",
      "publishedAt": "2026-04-30",
      "hearingStartDate": "2026-04-30",
      "hearingEndDate": "2026-05-14",
      "detailUrl": "https://www.eum.go.kr/web/cp/hr/hrPeopleHearDet.jsp?seq=4662&pageNo=2&zonenm=&startdt=&enddt=&chrgorg=&selSggCd=&select2=&select_3=&gosino=&mobile_yn=",
      "listPage": 2
    },
    {
      "seq": "4661",
      "title": "원주 도시관리계획(지구단위계획:단구지구) 결정(변경)(안) 열람&#8228;공고",
      "noticeNumber": "강원특별자치도 원주시 공고 제2026-1242호",
      "agency": "강원특별자치도 원주시 도시국 도시계획과",
      "publishedAt": "2026-04-30",
      "hearingStartDate": "2026-04-30",
      "hearingEndDate": "2026-05-14",
      "detailUrl": "https://www.eum.go.kr/web/cp/hr/hrPeopleHearDet.jsp?seq=4661&pageNo=2&zonenm=&startdt=&enddt=&chrgorg=&selSggCd=&select2=&select_3=&gosino=&mobile_yn=",
      "listPage": 2
    },
    {
      "seq": "4660",
      "title": "대전 도시관리계획(용도지구, 지구단위계획) 결정(변경)(안) 주민열람 공고",
      "noticeNumber": "대전광역시 공고 제2026-971호",
      "agency": "대전광역시 도시주택국 도시계획과",
      "publishedAt": "2026-04-29",
      "hearingStartDate": "2026-04-30",
      "hearingEndDate": "2026-05-14",
      "detailUrl": "https://www.eum.go.kr/web/cp/hr/hrPeopleHearDet.jsp?seq=4660&pageNo=2&zonenm=&startdt=&enddt=&chrgorg=&selSggCd=&select2=&select_3=&gosino=&mobile_yn=",
      "listPage": 2
    },
    {
      "seq": "4659",
      "title": "괴산 군관리계획(용도지역, 관광ㆍ휴양형 지구단위계획구역 및 계획) 결정(변경)(안) 주민 재열람 공고",
      "noticeNumber": "충청북도 괴산군 공고 제2026-524호",
      "agency": "충청북도 괴산군 농업건설국 도시건축과",
      "publishedAt": "2026-04-30",
      "hearingStartDate": "2026-04-30",
      "hearingEndDate": "2026-05-14",
      "detailUrl": "https://www.eum.go.kr/web/cp/hr/hrPeopleHearDet.jsp?seq=4659&pageNo=3&zonenm=&startdt=&enddt=&chrgorg=&selSggCd=&select2=&select_3=&gosino=&mobile_yn=",
      "listPage": 3
    },
    {
      "seq": "4647",
      "title": "동대문구 도시관리계획(도시계획시설: 도로, 학교) 결정(변경)(안) 열람공고",
      "noticeNumber": "서울특별시 동대문구 공고 제2026-660호",
      "agency": "서울특별시 동대문구 공간혁신국 도시계획과",
      "publishedAt": "2026-04-30",
      "hearingStartDate": "2026-04-30",
      "hearingEndDate": "2026-05-14",
      "detailUrl": "https://www.eum.go.kr/web/cp/hr/hrPeopleHearDet.jsp?seq=4647&pageNo=3&zonenm=&startdt=&enddt=&chrgorg=&selSggCd=&select2=&select_3=&gosino=&mobile_yn=",
      "listPage": 3
    },
    {
      "seq": "4641",
      "title": "인제 군관리계획[시설 : 주차장, 공간적 범위] 결정(변경)(안) 공람·공고",
      "noticeNumber": "강원특별자치도 인제군 공고 제2026-573호",
      "agency": "강원특별자치도 인제군",
      "publishedAt": "2026-04-30",
      "hearingStartDate": "2026-04-30",
      "hearingEndDate": "2026-05-15",
      "detailUrl": "https://www.eum.go.kr/web/cp/hr/hrPeopleHearDet.jsp?seq=4641&pageNo=3&zonenm=&startdt=&enddt=&chrgorg=&selSggCd=&select2=&select_3=&gosino=&mobile_yn=",
      "listPage": 3
    },
    {
      "seq": "4640",
      "title": "인제 군관리계획[용도지역 및 군계획시설(근린공원), 지구단위계획구역] 결정(변경)(안) 및 전략환경영향평가서(초안) 공람·공고",
      "noticeNumber": "강원특별자치도 인제군 공고 제2026-572호",
      "agency": "강원특별자치도 인제군",
      "publishedAt": "2026-04-30",
      "hearingStartDate": "2026-04-30",
      "hearingEndDate": "2026-05-15",
      "detailUrl": "https://www.eum.go.kr/web/cp/hr/hrPeopleHearDet.jsp?seq=4640&pageNo=3&zonenm=&startdt=&enddt=&chrgorg=&selSggCd=&select2=&select_3=&gosino=&mobile_yn=",
      "listPage": 3
    },
    {
      "seq": "4635",
      "title": "도시계획시설(도로) 결정(변경)을 위한 열람공고",
      "noticeNumber": "서울특별시 공고 제2026-1399호",
      "agency": "서울특별시 도시공간본부 시설계획과",
      "publishedAt": "2026-04-30",
      "hearingStartDate": "2026-04-30",
      "hearingEndDate": "2026-05-14",
      "detailUrl": "https://www.eum.go.kr/web/cp/hr/hrPeopleHearDet.jsp?seq=4635&pageNo=3&zonenm=&startdt=&enddt=&chrgorg=&selSggCd=&select2=&select_3=&gosino=&mobile_yn=",
      "listPage": 3
    },
    {
      "seq": "4677",
      "title": "공도 진사 도시계획시설(도로: 소로1-176호선, 소로2-269호선) 결정(변경)(안) 열람공고",
      "noticeNumber": "경기도 안성시 공고 제2026-1240호",
      "agency": "경기도 안성시 경제도시국",
      "publishedAt": "2026-04-29",
      "hearingStartDate": "2026-04-29",
      "hearingEndDate": "2026-05-13",
      "detailUrl": "https://www.eum.go.kr/web/cp/hr/hrPeopleHearDet.jsp?seq=4677&pageNo=3&zonenm=&startdt=&enddt=&chrgorg=&selSggCd=&select2=&select_3=&gosino=&mobile_yn=",
      "listPage": 3
    },
    {
      "seq": "4658",
      "title": "진안 군관리계획(군계획시설:도로) 결정(안) 주민공람 공고",
      "noticeNumber": "전북특별자치도 진안군 공고 제2026-522호",
      "agency": "전북특별자치도 진안군 건설교통과",
      "publishedAt": "2026-04-29",
      "hearingStartDate": "2026-04-29",
      "hearingEndDate": "2026-05-13",
      "detailUrl": "https://www.eum.go.kr/web/cp/hr/hrPeopleHearDet.jsp?seq=4658&pageNo=3&zonenm=&startdt=&enddt=&chrgorg=&selSggCd=&select2=&select_3=&gosino=&mobile_yn=",
      "listPage": 3
    },
    {
      "seq": "4656",
      "title": "광양 도시관리계획(망덕지구 지구단위계획) 결정(변경)(안) 열람공고",
      "noticeNumber": "전라남도 광양시 공고 제2026-1065호",
      "agency": "전라남도 광양시 안전도시국 도시과",
      "publishedAt": "2026-04-29",
      "hearingStartDate": "2026-04-29",
      "hearingEndDate": "2026-05-13",
      "detailUrl": "https://www.eum.go.kr/web/cp/hr/hrPeopleHearDet.jsp?seq=4656&pageNo=3&zonenm=&startdt=&enddt=&chrgorg=&selSggCd=&select2=&select_3=&gosino=&mobile_yn=",
      "listPage": 3
    },
    {
      "seq": "4654",
      "title": "도시관리계획(시설:학교) 결정(폐지)(안) 열람공고",
      "noticeNumber": "부산광역시 부산진구 공고 제2026-634호",
      "agency": "부산광역시 부산진구 도시관리국 건설과",
      "publishedAt": "2026-04-29",
      "hearingStartDate": "2026-04-29",
      "hearingEndDate": "2026-05-13",
      "detailUrl": "https://www.eum.go.kr/web/cp/hr/hrPeopleHearDet.jsp?seq=4654&pageNo=3&zonenm=&startdt=&enddt=&chrgorg=&selSggCd=&select2=&select_3=&gosino=&mobile_yn=",
      "listPage": 3
    },
    {
      "seq": "4657",
      "title": "2030년 광양 도시관리계획(재정비) 결정(변경)(안) 및 전략환경영향평가서(초안) 열람공고",
      "noticeNumber": "전라남도 광양시 공고 제2026-1047호",
      "agency": "전라남도 광양시 안전도시국 도시과",
      "publishedAt": "2026-04-28",
      "hearingStartDate": "2026-04-28",
      "hearingEndDate": "2026-05-19",
      "detailUrl": "https://www.eum.go.kr/web/cp/hr/hrPeopleHearDet.jsp?seq=4657&pageNo=3&zonenm=&startdt=&enddt=&chrgorg=&selSggCd=&select2=&select_3=&gosino=&mobile_yn=",
      "listPage": 3
    },
    {
      "seq": "4643",
      "title": "군포도시관리계획(벌터마벨·대야·당정2·당정대영·지구단위계획) 결정(변경)(안) 주민공람 공고",
      "noticeNumber": "경기도 군포시 공고 제2026-609호",
      "agency": "경기도 군포시 도시주택국 도시계획과",
      "publishedAt": "2026-04-28",
      "hearingStartDate": "2026-04-28",
      "hearingEndDate": "2026-05-20",
      "detailUrl": "https://www.eum.go.kr/web/cp/hr/hrPeopleHearDet.jsp?seq=4643&pageNo=4&zonenm=&startdt=&enddt=&chrgorg=&selSggCd=&select2=&select_3=&gosino=&mobile_yn=",
      "listPage": 4
    },
    {
      "seq": "4642",
      "title": "양주 도시관리계획(지구단위계획:일영지구) 결정(변경)(안) 주민공람 공고",
      "noticeNumber": "경기도 양주시 공고 제2026-1153호",
      "agency": "경기도 양주시 도시주택국 도시과",
      "publishedAt": "2026-04-28",
      "hearingStartDate": "2026-04-28",
      "hearingEndDate": "2026-05-13",
      "detailUrl": "https://www.eum.go.kr/web/cp/hr/hrPeopleHearDet.jsp?seq=4642&pageNo=4&zonenm=&startdt=&enddt=&chrgorg=&selSggCd=&select2=&select_3=&gosino=&mobile_yn=",
      "listPage": 4
    },
    {
      "seq": "4639",
      "title": "고양 도시관리계획(일산동 2148번지 일대 지구단위계획) 결정(변경)(안)  공람 공고",
      "noticeNumber": "경기도 고양시 공고 제2026-1168호",
      "agency": "경기도 고양시 도시주택정책실 도시계획정책관",
      "publishedAt": "2026-04-28",
      "hearingStartDate": "2026-04-28",
      "hearingEndDate": "2026-05-12",
      "detailUrl": "https://www.eum.go.kr/web/cp/hr/hrPeopleHearDet.jsp?seq=4639&pageNo=4&zonenm=&startdt=&enddt=&chrgorg=&selSggCd=&select2=&select_3=&gosino=&mobile_yn=",
      "listPage": 4
    },
    {
      "seq": "4637",
      "title": "논산 도시관리계획(용도구역, 도시계획시설, 공원조성계획) 결정(변경)(안) 공람공고",
      "noticeNumber": "충청남도 논산시 공고 제2026-970호",
      "agency": "충청남도 논산시 건설미래국 도시주택과",
      "publishedAt": "2026-04-27",
      "hearingStartDate": "2026-04-27",
      "hearingEndDate": "2026-05-12",
      "detailUrl": "https://www.eum.go.kr/web/cp/hr/hrPeopleHearDet.jsp?seq=4637&pageNo=4&zonenm=&startdt=&enddt=&chrgorg=&selSggCd=&select2=&select_3=&gosino=&mobile_yn=",
      "listPage": 4
    },
    {
      "seq": "4620",
      "title": "도시관리계획(도시계획시설: 도로, 문화공원) 및 공원조성계획 결정(변경)(안) 재열람 공고",
      "noticeNumber": "충청남도 서산시 공고 제2026-1286호",
      "agency": "충청남도 서산시",
      "publishedAt": "2026-04-27",
      "hearingStartDate": "2026-04-27",
      "hearingEndDate": "2026-05-20",
      "detailUrl": "https://www.eum.go.kr/web/cp/hr/hrPeopleHearDet.jsp?seq=4620&pageNo=4&zonenm=&startdt=&enddt=&chrgorg=&selSggCd=&select2=&select_3=&gosino=&mobile_yn=",
      "listPage": 4
    },
    {
      "seq": "4610",
      "title": "도시관리계획(용도구역: 수산자원보호구역) 결정(변경)(안) 열람 공고",
      "noticeNumber": "충청남도 서산시 공고 제2026-1269호",
      "agency": "충청남도 서산시 건설도시국 도시과",
      "publishedAt": "2026-04-27",
      "hearingStartDate": "2026-04-27",
      "hearingEndDate": "2026-05-19",
      "detailUrl": "https://www.eum.go.kr/web/cp/hr/hrPeopleHearDet.jsp?seq=4610&pageNo=4&zonenm=&startdt=&enddt=&chrgorg=&selSggCd=&select2=&select_3=&gosino=&mobile_yn=",
      "listPage": 4
    },
    {
      "seq": "4609",
      "title": "도시관리계획(대산도시계획시설:체육시설) 결정(변경)(안) 열람 공고",
      "noticeNumber": "충청남도 서산시 공고 제2026-1227호",
      "agency": "충청남도 서산시 건설도시국 도시과",
      "publishedAt": "2026-04-24",
      "hearingStartDate": "2026-04-27",
      "hearingEndDate": "2026-05-20",
      "detailUrl": "https://www.eum.go.kr/web/cp/hr/hrPeopleHearDet.jsp?seq=4609&pageNo=4&zonenm=&startdt=&enddt=&chrgorg=&selSggCd=&select2=&select_3=&gosino=&mobile_yn=",
      "listPage": 4
    },
    {
      "seq": "4650",
      "title": "장위11-2구역 가로주택정비사업 사업시행계획변경인가를 위한 공람공고",
      "noticeNumber": "서울특별시 공고 제2026-752호",
      "agency": "서울특별시 성북구 도시관리국 신속도시정비과",
      "publishedAt": "2026-04-24",
      "hearingStartDate": "2026-04-24",
      "hearingEndDate": "2026-05-08",
      "detailUrl": "https://www.eum.go.kr/web/cp/hr/hrPeopleHearDet.jsp?seq=4650&pageNo=4&zonenm=&startdt=&enddt=&chrgorg=&selSggCd=&select2=&select_3=&gosino=&mobile_yn=",
      "listPage": 4
    },
    {
      "seq": "4636",
      "title": "잠실아파트지구 개발기본계획 결정(변경)(안),장미1,2,3차아파트 주택재건축정비사업 정비구역 및 정비계획(변경)(안)에 대한 재공람？공고",
      "noticeNumber": "서울특별시 송파구 공고 제2026-795호",
      "agency": "서울특별시 송파구 도시현대화국 주택사업과",
      "publishedAt": "2026-04-24",
      "hearingStartDate": "2026-04-24",
      "hearingEndDate": "2026-05-25",
      "detailUrl": "https://www.eum.go.kr/web/cp/hr/hrPeopleHearDet.jsp?seq=4636&pageNo=4&zonenm=&startdt=&enddt=&chrgorg=&selSggCd=&select2=&select_3=&gosino=&mobile_yn=",
      "listPage": 4
    },
    {
      "seq": "4632",
      "title": "평택 도시관리계획[지구단위계획 재정비_군문택지지구 등 51개 지구] 결정(변경)(안) 공람 공고",
      "noticeNumber": "경기도 평택시 공고 제2026-1484호",
      "agency": "경기도 평택시",
      "publishedAt": "2026-04-24",
      "hearingStartDate": "2026-04-24",
      "hearingEndDate": "2026-05-08",
      "detailUrl": "https://www.eum.go.kr/web/cp/hr/hrPeopleHearDet.jsp?seq=4632&pageNo=4&zonenm=&startdt=&enddt=&chrgorg=&selSggCd=&select2=&select_3=&gosino=&mobile_yn=",
      "listPage": 4
    },
    {
      "seq": "4630",
      "title": "의령군관리계획[교통시설:도로(소로2-111호선)] 결정을 위한 공람 공고",
      "noticeNumber": "경상남도 의령군 공고 제2026-521호",
      "agency": "경상남도 의령군 산업건설국 도시재생과",
      "publishedAt": "2026-04-24",
      "hearingStartDate": "2026-04-24",
      "hearingEndDate": "2026-05-08",
      "detailUrl": "https://www.eum.go.kr/web/cp/hr/hrPeopleHearDet.jsp?seq=4630&pageNo=5&zonenm=&startdt=&enddt=&chrgorg=&selSggCd=&select2=&select_3=&gosino=&mobile_yn=",
      "listPage": 5
    },
    {
      "seq": "4626",
      "title": "김제 도시계획시설사업(근린광장) 사업시행자지정 및 실시계획인가전 열람공고[동헌 앞 다목적광장 조성사업]",
      "noticeNumber": "전북특별자치도 김제시 공고 제2026-539호",
      "agency": "전북특별자치도 김제시 도시건설국 도시과",
      "publishedAt": "2026-04-24",
      "hearingStartDate": "2026-04-24",
      "hearingEndDate": "2026-05-08",
      "detailUrl": "https://www.eum.go.kr/web/cp/hr/hrPeopleHearDet.jsp?seq=4626&pageNo=5&zonenm=&startdt=&enddt=&chrgorg=&selSggCd=&select2=&select_3=&gosino=&mobile_yn=",
      "listPage": 5
    },
    {
      "seq": "4615",
      "title": "원주 도시관리계획(주차장73호) 결정(변경)(안) 주민 열람·공고",
      "noticeNumber": "강원도 원주시 공고 제2026-1193호",
      "agency": "강원특별자치도 원주시 도시국 도시계획과",
      "publishedAt": "2026-04-24",
      "hearingStartDate": "2026-04-24",
      "hearingEndDate": "2026-05-11",
      "detailUrl": "https://www.eum.go.kr/web/cp/hr/hrPeopleHearDet.jsp?seq=4615&pageNo=5&zonenm=&startdt=&enddt=&chrgorg=&selSggCd=&select2=&select_3=&gosino=&mobile_yn=",
      "listPage": 5
    },
    {
      "seq": "4596",
      "title": "남원 도시관리계획(도시계획시설:역사공원) 조성계획 결정(변경)(안) 주민 의견청취 열람공고",
      "noticeNumber": "전북특별자치도 남원시 공고 제2026-1044호",
      "agency": "전북특별자치도 남원시 안전건설국 도시과",
      "publishedAt": "2026-04-24",
      "hearingStartDate": "2026-04-24",
      "hearingEndDate": "2026-05-08",
      "detailUrl": "https://www.eum.go.kr/web/cp/hr/hrPeopleHearDet.jsp?seq=4596&pageNo=5&zonenm=&startdt=&enddt=&chrgorg=&selSggCd=&select2=&select_3=&gosino=&mobile_yn=",
      "listPage": 5
    },
    {
      "seq": "4653",
      "title": "월드컵근린공원 조성계획 변경(안) 열람공고",
      "noticeNumber": "서울특별시 공고 제2026-1352호",
      "agency": "서울특별시 서부공원여가센터 시설과",
      "publishedAt": "2026-04-23",
      "hearingStartDate": "2026-04-23",
      "hearingEndDate": "2026-05-07",
      "detailUrl": "https://www.eum.go.kr/web/cp/hr/hrPeopleHearDet.jsp?seq=4653&pageNo=5&zonenm=&startdt=&enddt=&chrgorg=&selSggCd=&select2=&select_3=&gosino=&mobile_yn=",
      "listPage": 5
    },
    {
      "seq": "4625",
      "title": "예천 군계획시설(공원) 실시계획 인가를 위한 재열람공고",
      "noticeNumber": "경상북도 예천군 공고 제2026-683호",
      "agency": "경상북도 예천군 도시과",
      "publishedAt": "2026-04-23",
      "hearingStartDate": "2026-04-23",
      "hearingEndDate": "2026-05-07",
      "detailUrl": "https://www.eum.go.kr/web/cp/hr/hrPeopleHearDet.jsp?seq=4625&pageNo=5&zonenm=&startdt=&enddt=&chrgorg=&selSggCd=&select2=&select_3=&gosino=&mobile_yn=",
      "listPage": 5
    },
    {
      "seq": "4624",
      "title": "도시관리계획(워커힐아파트 일대  지구단위계획구역  지정 및 계획) 결정을 위한 열람 공고",
      "noticeNumber": "서울특별시 광진구 공고 제2026-574호",
      "agency": "서울특별시 광진구 미래도시국 주거사업과",
      "publishedAt": "2026-04-23",
      "hearingStartDate": "2026-04-23",
      "hearingEndDate": "2026-05-07",
      "detailUrl": "https://www.eum.go.kr/web/cp/hr/hrPeopleHearDet.jsp?seq=4624&pageNo=5&zonenm=&startdt=&enddt=&chrgorg=&selSggCd=&select2=&select_3=&gosino=&mobile_yn=",
      "listPage": 5
    },
    {
      "seq": "4623",
      "title": "[재공고] 용인도시관리계획(연구시설7호 금호타이어) 결정(변경) 및 사업시행자 지정, 실시계획 인가 열람",
      "noticeNumber": "경기도 용인시 공고 제2026-1412호",
      "agency": "경기도 용인시 도시정책실 도시정보과",
      "publishedAt": "2026-04-23",
      "hearingStartDate": "2026-04-23",
      "hearingEndDate": "2026-05-08",
      "detailUrl": "https://www.eum.go.kr/web/cp/hr/hrPeopleHearDet.jsp?seq=4623&pageNo=5&zonenm=&startdt=&enddt=&chrgorg=&selSggCd=&select2=&select_3=&gosino=&mobile_yn=",
      "listPage": 5
    },
    {
      "seq": "4621",
      "title": "백두대간 힐링 펫빌리지 진입도로 개설을 위한  봉화 군관리계획(도로, 지구단위계획) 결정(변경) 수립 열람공고",
      "noticeNumber": "경상북도 봉화군 공고 제2026-478호",
      "agency": "경상북도 봉화군 문화관광과",
      "publishedAt": "2026-04-23",
      "hearingStartDate": "2026-04-23",
      "hearingEndDate": "2026-05-07",
      "detailUrl": "https://www.eum.go.kr/web/cp/hr/hrPeopleHearDet.jsp?seq=4621&pageNo=5&zonenm=&startdt=&enddt=&chrgorg=&selSggCd=&select2=&select_3=&gosino=&mobile_yn=",
      "listPage": 5
    },
    {
      "seq": "4619",
      "title": "의령군관리계획(지구단위계획구역 및 지구단위계획:서동행정타운) 결정(변경)(안) 재공람·공고",
      "noticeNumber": "경상남도 의령군 공고 제2026-511호",
      "agency": "경상남도 의령군 산업건설국 도시재생과",
      "publishedAt": "2026-04-23",
      "hearingStartDate": "2026-04-23",
      "hearingEndDate": "2026-05-07",
      "detailUrl": "https://www.eum.go.kr/web/cp/hr/hrPeopleHearDet.jsp?seq=4619&pageNo=6&zonenm=&startdt=&enddt=&chrgorg=&selSggCd=&select2=&select_3=&gosino=&mobile_yn=",
      "listPage": 6
    },
    {
      "seq": "4618",
      "title": "2035년 영월 군기본계획 일부변경 승인 열람 공고",
      "noticeNumber": "강원특별자치도 영월군 공고 제2026-627호",
      "agency": "강원특별자치도 영월군 지역개발실",
      "publishedAt": "2026-04-23",
      "hearingStartDate": "2026-04-23",
      "hearingEndDate": "2026-05-26",
      "detailUrl": "https://www.eum.go.kr/web/cp/hr/hrPeopleHearDet.jsp?seq=4618&pageNo=6&zonenm=&startdt=&enddt=&chrgorg=&selSggCd=&select2=&select_3=&gosino=&mobile_yn=",
      "listPage": 6
    },
    {
      "seq": "4617",
      "title": "도시계획시설(도로) 결정(안) 열람공고",
      "noticeNumber": "서울특별시 노원구 공고 제2026-738호",
      "agency": "서울특별시 노원구 도시계획국 도시관리과",
      "publishedAt": "2026-04-23",
      "hearingStartDate": "2026-04-23",
      "hearingEndDate": "2026-05-07",
      "detailUrl": "https://www.eum.go.kr/web/cp/hr/hrPeopleHearDet.jsp?seq=4617&pageNo=6&zonenm=&startdt=&enddt=&chrgorg=&selSggCd=&select2=&select_3=&gosino=&mobile_yn=",
      "listPage": 6
    },
    {
      "seq": "4616",
      "title": "도시관리계획(소로3-93) 결정[변경](안) 입안에 따른 주민 공람 공고",
      "noticeNumber": "경기도 남양주시 공고 제2026-985호",
      "agency": "경기도 남양주시 도시국 도시정책과",
      "publishedAt": "2026-04-23",
      "hearingStartDate": "2026-04-23",
      "hearingEndDate": "2026-05-07",
      "detailUrl": "https://www.eum.go.kr/web/cp/hr/hrPeopleHearDet.jsp?seq=4616&pageNo=6&zonenm=&startdt=&enddt=&chrgorg=&selSggCd=&select2=&select_3=&gosino=&mobile_yn=",
      "listPage": 6
    },
    {
      "seq": "4614",
      "title": "여의도 아파트지구 개발기본계획 및 도시관리계획 변경(안), 여의도 삼익아파트 재건축 정비구역·정비계획 결정(변경)(안), 지구단위계획 ...",
      "noticeNumber": "서울특별시 영등포구 공고 제2026-853호",
      "agency": "서울특별시 영등포구 도시공간국 재건축사업과",
      "publishedAt": "2026-04-23",
      "hearingStartDate": "2026-04-23",
      "hearingEndDate": "2026-05-27",
      "detailUrl": "https://www.eum.go.kr/web/cp/hr/hrPeopleHearDet.jsp?seq=4614&pageNo=6&zonenm=&startdt=&enddt=&chrgorg=&selSggCd=&select2=&select_3=&gosino=&mobile_yn=",
      "listPage": 6
    },
    {
      "seq": "4613",
      "title": "여의도 아파트지구 개발기본계획 및 도시관리계획 변경(안), 여의도 은하아파트 재건축 정비구역·정비계획 결정(변경)(안), 지구단위계획 ...",
      "noticeNumber": "서울특별시 영등포구 공고 제2026-854호",
      "agency": "서울특별시 영등포구 도시공간국 재건축사업과",
      "publishedAt": "2026-04-23",
      "hearingStartDate": "2026-04-23",
      "hearingEndDate": "2026-05-27",
      "detailUrl": "https://www.eum.go.kr/web/cp/hr/hrPeopleHearDet.jsp?seq=4613&pageNo=6&zonenm=&startdt=&enddt=&chrgorg=&selSggCd=&select2=&select_3=&gosino=&mobile_yn=",
      "listPage": 6
    },
    {
      "seq": "4604",
      "title": "도시관리계획(도시계획시설:도로) 결정(변경)(안) 재열람 공고",
      "noticeNumber": "서울특별시 공고 제2026-1354호",
      "agency": "서울특별시 미래공간기획관 미래공간담당관",
      "publishedAt": "2026-04-23",
      "hearingStartDate": "2026-04-23",
      "hearingEndDate": "2026-05-07",
      "detailUrl": "https://www.eum.go.kr/web/cp/hr/hrPeopleHearDet.jsp?seq=4604&pageNo=6&zonenm=&startdt=&enddt=&chrgorg=&selSggCd=&select2=&select_3=&gosino=&mobile_yn=",
      "listPage": 6
    },
    {
      "seq": "4603",
      "title": "마석우4지구(원도심) 도시관리계획 변경 결정(안)  주민공람 공고",
      "noticeNumber": "경기도 남양주시 공고 제2026-979호",
      "agency": "경기도 남양주시 도시국 도시정책과",
      "publishedAt": "2026-04-23",
      "hearingStartDate": "2026-04-23",
      "hearingEndDate": "2026-05-07",
      "detailUrl": "https://www.eum.go.kr/web/cp/hr/hrPeopleHearDet.jsp?seq=4603&pageNo=6&zonenm=&startdt=&enddt=&chrgorg=&selSggCd=&select2=&select_3=&gosino=&mobile_yn=",
      "listPage": 6
    },
    {
      "seq": "4584",
      "title": "도시관리계획(도시계획시설:시장) 결정(변경)(안) 열람공고",
      "noticeNumber": "서울특별시 성동구 공고 제2026-619호",
      "agency": "서울특별시 성동구 도시관리국 도시계획과",
      "publishedAt": "2026-04-23",
      "hearingStartDate": "2026-04-23",
      "hearingEndDate": "2026-05-07",
      "detailUrl": "https://www.eum.go.kr/web/cp/hr/hrPeopleHearDet.jsp?seq=4584&pageNo=6&zonenm=&startdt=&enddt=&chrgorg=&selSggCd=&select2=&select_3=&gosino=&mobile_yn=",
      "listPage": 6
    },
    {
      "seq": "4651",
      "title": "마포로5구역 제10·11지구 도시정비형 재개발사업  사업시행계획(변경)인가를 위한 공람·공고",
      "noticeNumber": "서울특별시 중구 공고 제2026-461호",
      "agency": "서울특별시 중구 도시관리국 도심정비과",
      "publishedAt": "2026-04-22",
      "hearingStartDate": "2026-04-22",
      "hearingEndDate": "2026-05-06",
      "detailUrl": "https://www.eum.go.kr/web/cp/hr/hrPeopleHearDet.jsp?seq=4651&pageNo=6&zonenm=&startdt=&enddt=&chrgorg=&selSggCd=&select2=&select_3=&gosino=&mobile_yn=",
      "listPage": 6
    },
    {
      "seq": "4608",
      "title": "이천 도시관리계획[지구단위계획(주거형:신원지구)]결정(변경)(안) 주민공람·공고",
      "noticeNumber": "경기도 이천시 공고 제2026-1224호",
      "agency": "경기도 이천시 도시주택국 도시과",
      "publishedAt": "2026-04-22",
      "hearingStartDate": "2026-04-22",
      "hearingEndDate": "2026-05-06",
      "detailUrl": "https://www.eum.go.kr/web/cp/hr/hrPeopleHearDet.jsp?seq=4608&pageNo=7&zonenm=&startdt=&enddt=&chrgorg=&selSggCd=&select2=&select_3=&gosino=&mobile_yn=",
      "listPage": 7
    },
    {
      "seq": "4605",
      "title": "창원도시관리계획(도로) 결정(변경)(안) 열람 공고",
      "noticeNumber": "경상남도 창원시 공고 제2026-852호",
      "agency": "경상남도 창원시(통합) 도시정책국 도시계획과",
      "publishedAt": "2026-04-22",
      "hearingStartDate": "2026-04-22",
      "hearingEndDate": "2026-05-12",
      "detailUrl": "https://www.eum.go.kr/web/cp/hr/hrPeopleHearDet.jsp?seq=4605&pageNo=7&zonenm=&startdt=&enddt=&chrgorg=&selSggCd=&select2=&select_3=&gosino=&mobile_yn=",
      "listPage": 7
    },
    {
      "seq": "4583",
      "title": "도시관리계획(안) 재열람공고(금정구 구서동 481-1번지 일원 문화시설)",
      "noticeNumber": "부산광역시 공고 제2026-1373호",
      "agency": "부산광역시 도시공간계획국 도시공간조성과",
      "publishedAt": "2026-04-22",
      "hearingStartDate": "2026-04-22",
      "hearingEndDate": "2026-05-06",
      "detailUrl": "https://www.eum.go.kr/web/cp/hr/hrPeopleHearDet.jsp?seq=4583&pageNo=7&zonenm=&startdt=&enddt=&chrgorg=&selSggCd=&select2=&select_3=&gosino=&mobile_yn=",
      "listPage": 7
    },
    {
      "seq": "4599",
      "title": "홍문3지구 도시개발구역 지정(안) 및 개발계획 수립(안) 공람·공고",
      "noticeNumber": "경기도 여주시 공고 제2026-794호",
      "agency": "경기도 여주시 도시건설국 도시개발과",
      "publishedAt": "2026-04-21",
      "hearingStartDate": "2026-04-20",
      "hearingEndDate": "2026-05-07",
      "detailUrl": "https://www.eum.go.kr/web/cp/hr/hrPeopleHearDet.jsp?seq=4599&pageNo=7&zonenm=&startdt=&enddt=&chrgorg=&selSggCd=&select2=&select_3=&gosino=&mobile_yn=",
      "listPage": 7
    },
    {
      "seq": "4567",
      "title": "도시관리계획(구월 지구단위계획) 결정(변경)(안) 재공고·열람",
      "noticeNumber": "인천광역시 공고 제2026-951호",
      "agency": "인천광역시 도시계획국 도시관리과",
      "publishedAt": "2026-04-20",
      "hearingStartDate": "2026-04-20",
      "hearingEndDate": "2026-05-06",
      "detailUrl": "https://www.eum.go.kr/web/cp/hr/hrPeopleHearDet.jsp?seq=4567&pageNo=8&zonenm=&startdt=&enddt=&chrgorg=&selSggCd=&select2=&select_3=&gosino=&mobile_yn=",
      "listPage": 8
    },
    {
      "seq": "4572",
      "title": "묵현8지구 도시관리계획 결정(변경)(안) 및 전략환경영향평가서(초안) 공람 및 주민설명회 개최 공고",
      "noticeNumber": "경기도 남양주시 공고 제2026-952호",
      "agency": "경기도 남양주시 도시국 도시정책과",
      "publishedAt": "2026-04-17",
      "hearingStartDate": "2026-04-17",
      "hearingEndDate": "2026-05-07",
      "detailUrl": "https://www.eum.go.kr/web/cp/hr/hrPeopleHearDet.jsp?seq=4572&pageNo=8&zonenm=&startdt=&enddt=&chrgorg=&selSggCd=&select2=&select_3=&gosino=&mobile_yn=",
      "listPage": 8
    }
  ]
}